legendary/__init__.py
legendary/cli.py
legendary/core.py
legendary/api/__init__.py
legendary/api/egs.py
legendary/api/lgd.py
legendary/downloader/__init__.py
legendary/downloader/mp/__init__.py
legendary/downloader/mp/manager.py
legendary/downloader/mp/workers.py
legendary/lfs/__init__.py
legendary/lfs/crossover.py
legendary/lfs/egl.py
legendary/lfs/eos.py
legendary/lfs/lgndry.py
legendary/lfs/utils.py
legendary/lfs/windows_helpers.py
legendary/lfs/wine_helpers.py
legendary/models/__init__.py
legendary/models/chunk.py
legendary/models/config.py
legendary/models/downloading.py
legendary/models/egl.py
legendary/models/exceptions.py
legendary/models/game.py
legendary/models/gql.py
legendary/models/json_manifest.py
legendary/models/manifest.py
legendary/utils/__init__.py
legendary/utils/aliasing.py
legendary/utils/cli.py
legendary/utils/custom_parser.py
legendary/utils/egl_crypt.py
legendary/utils/env.py
legendary/utils/game_workarounds.py
legendary/utils/rolling_hash.py
legendary/utils/savegame_helper.py
legendary/utils/selective_dl.py
legendary/utils/webview_login.py
legendary_gl-0.20.34.dist-info/LICENSE
legendary_gl-0.20.34.dist-info/METADATA
legendary_gl-0.20.34.dist-info/WHEEL
legendary_gl-0.20.34.dist-info/entry_points.txt
legendary_gl-0.20.34.dist-info/top_level.txt
legendary_gl-0.20.34.dist-info/RECORD
