Metadata-Version: 2.1
Name: legendary-gl
Version: 0.20.34
Summary: Free and open-source replacement for the Epic Games Launcher application
Home-page: https://github.com/derrod/legendary
Author: Rodney
Author-email: rodney@rodney.io
License: GPL-3
Classifier: License :: OSI Approved :: GNU General Public License v3 or later (GPLv3+)
Classifier: Programming Language :: Python
Classifier: Programming Language :: Python :: 3.9
Classifier: Operating System :: POSIX :: Linux
Classifier: Operating System :: Microsoft
Classifier: Intended Audience :: End Users/Desktop
Classifier: Topic :: Games/Entertainment
Classifier: Development Status :: 4 - Beta
Requires-Python: >=3.9
Provides-Extra: webview
Provides-Extra: webview_gtk
License-File: LICENSE
